{
  "editor:toggle-highlight": [
    {
      "modifiers": [
        "Alt"
      ],
      "key": "H"
    }
  ],
  "insert-template": [],
  "file-explorer:move-file": [
    {
      "modifiers": [
        "Alt"
      ],
      "key": "M"
    }
  ],
  "obsidian-hotkeys-for-templates:defaultInfo.md": [
    {
      "modifiers": [
        "Alt"
      ],
      "key": "I"
    }
  ],
  "obsidian-hotkeys-for-templates:defaultDaily.md": [
    {
      "modifiers": [
        "Alt"
      ],
      "key": "D"
    }
  ],
  "obsidian-hotkeys-for-templates:defaultBar.md": [
    {
      "modifiers": [
        "Alt"
      ],
      "key": "B"
    }
  ],
  "obsidian-hotkeys-for-templates:defaultProject.md": [
    {
      "modifiers": [
        "Alt"
      ],
      "key": "P"
    }
  ],
  "obsidian-fullscreen-plugin:fullscreen-focus": [
    {
      "modifiers": [
        "Alt",
        "Mod"
      ],
      "key": "X"
    }
  ],
  "editor:cycle-list-checklist": [
    {
      "modifiers": [
        "Mod"
      ],
      "key": "L"
    }
  ],
  "editor:toggle-checklist-status": [],
  "editor:delete-paragraph": []
}