{
  "main": {
    "id": "03398ca5a89be6a0",
    "type": "split",
    "children": [
      {
        "id": "334ed700b7550254",
        "type": "tabs",
        "children": [
          {
            "id": "7a5861cf8bed6f97",
            "type": "leaf",
            "state": {
              "type": "empty",
              "state": {},
              "icon": "lucide-file",
              "title": "New tab"
            }
          }
        ]
      }
    ],
    "direction": "vertical"
  },
  "left": {
    "id": "1d87dde4b2aca429",
    "type": "split",
    "children": [
      {
        "id": "386c8ef6f51c00be",
        "type": "tabs",
        "children": [
          {
            "id": "1e71e1b18519cb23",
            "type": "leaf",
            "state": {
              "type": "file-explorer",
              "state": {
                "sortOrder": "alphabetical"
              },
              "icon": "lucide-folder-closed",
              "title": "Files"
            }
          },
          {
            "id": "46951a0be9449dd7",
            "type": "leaf",
            "state": {
              "type": "search",
              "state": {
                "query": "",
                "matchingCase": false,
                "explainSearch": false,
                "collapseAll": true,
                "extraContext": false,
                "sortOrder": "alphabetical"
              },
              "icon": "lucide-search",
              "title": "Search"
            }
          },
          {
            "id": "50b9f14c995c8721",
            "type": "leaf",
            "state": {
              "type": "starred",
              "state": {},
              "icon": "lucide-file",
              "title": "Plugin no longer active"
            }
          },
          {
            "id": "b9b9f43c78107f40",
            "type": "leaf",
            "state": {
              "type": "bookmarks",
              "state": {},
              "icon": "lucide-bookmark",
              "title": "Bookmarks"
            }
          }
        ]
      }
    ],
    "direction": "horizontal",
    "width": 239.5,
    "collapsed": true
  },
  "right": {
    "id": "8df90fafb50945f7",
    "type": "split",
    "children": [
      {
        "id": "34ab9a8db53ac460",
        "type": "tabs",
        "children": [
          {
            "id": "4302f099b1b29e7c",
            "type": "leaf",
            "state": {
              "type": "backlink",
              "state": {
                "file": "Teino/Novels/Movies/注意点.md",
                "collapseAll": true,
                "extraContext": true,
                "sortOrder": "alphabetical",
                "showSearch": false,
                "searchQuery": "",
                "backlinkCollapsed": false,
                "unlinkedCollapsed": false
              },
              "icon": "links-coming-in",
              "title": "Backlinks for 注意点"
            }
          },
          {
            "id": "366df2a18d1f34bb",
            "type": "leaf",
            "state": {
              "type": "outgoing-link",
              "state": {
                "file": "Teino/Novels/Movies/注意点.md",
                "linksCollapsed": true,
                "unlinkedCollapsed": false
              },
              "icon": "links-going-out",
              "title": "Outgoing links from 注意点"
            }
          },
          {
            "id": "d4f4e32cf95a7098",
            "type": "leaf",
            "state": {
              "type": "tag",
              "state": {
                "sortOrder": "alphabetical",
                "useHierarchy": true
              },
              "icon": "lucide-tags",
              "title": "Tags"
            }
          },
          {
            "id": "7f4d402b29dc13d9",
            "type": "leaf",
            "state": {
              "type": "localgraph",
              "state": {
                "options": {
                  "collapse-filter": true,
                  "search": "",
                  "localJumps": 1,
                  "localBacklinks": true,
                  "localForelinks": true,
                  "localInterlinks": false,
                  "showTags": false,
                  "showAttachments": false,
                  "hideUnresolved": false,
                  "collapse-color-groups": true,
                  "colorGroups": [],
                  "collapse-display": true,
                  "showArrow": true,
                  "textFadeMultiplier": 0,
                  "nodeSizeMultiplier": 1.00042735042735,
                  "lineSizeMultiplier": 1.50299145299145,
                  "collapse-forces": false,
                  "centerStrength": 0.502941176470588,
                  "repelStrength": 10,
                  "linkStrength": 1,
                  "linkDistance": 250,
                  "scale": 0.8854989543150436,
                  "close": false
                }
              },
              "icon": "lucide-git-fork",
              "title": "Graph view"
            }
          },
          {
            "id": "c1872ec613792c9c",
            "type": "leaf",
            "state": {
              "type": "git-view",
              "state": {},
              "icon": "git-pull-request",
              "title": "Source Control"
            }
          },
          {
            "id": "edf0710c3abb8afb",
            "type": "leaf",
            "state": {
              "type": "advanced-tables-toolbar",
              "state": {},
              "icon": "spreadsheet",
              "title": "Advanced Tables"
            }
          }
        ],
        "currentTab": 4
      }
    ],
    "direction": "horizontal",
    "width": 304.5,
    "collapsed": true
  },
  "left-ribbon": {
    "hiddenItems": {
      "switcher:Open quick switcher": false,
      "graph:Open graph view": false,
      "canvas:Create new canvas": false,
      "daily-notes:Open today's daily note": false,
      "templates:Insert template": false,
      "command-palette:Open command palette": false,
      "random-note:Open random note": false,
      "table-editor-obsidian:Advanced Tables Toolbar": false,
      "obsidian-git:Open Git source control": false
    }
  },
  "active": "7a5861cf8bed6f97",
  "lastOpenFiles": [
    "Teino/Bar/Program/Markdown.md",
    "Teino/image/Pasted image 20241213223122.png",
    "Teino/Daily_Note/2024-12-13 FX.md",
    "Teino/Daily_Note/2024-12-13.md",
    "Teino/Bar/Program/JavaScript and TypeScript.md",
    "Others/Anki_Language.md",
    "Others/CEDEC,GDC.md",
    "Others/【Unity】ゲームオブジェクトの基礎（生成・削除・非表示など）から公式リファレンスまで解説決定版！  XR-Hub.md",
    "Others/【Git】基本コマンド - Qiita.md",
    "Others/Achivement.md",
    "Teino/Info/人らしく生きるってのの.md",
    "Daily_Note/2023-05-24.md",
    "Daily_Note/2024-05-24.md",
    "Others/Summareading/Template/TagWall.md",
    "Daily_Note",
    "Teino/Info/Neovim plugins.md",
    "Yeolumar/ZettelIdea/もしも全ての声明が受け入れられ.md",
    "Teino/Bar/Framework/Hugo.md",
    "Others/Anki Language English.md",
    "Others/All Explanation.md",
    "Others/Summareading/派生から基底のコンストラクタで初期化.md",
    "Others/Summareading/新しいBPプレーンを作る.md",
    "Others/Summareading/デフォルトARプロジェクトが動かない.md",
    "Others/Summareading/デフォルトコンストラクタを持たないクラスの初期化.md",
    "Others/Summareading/Wifi ADB devices.md",
    "Others/Summareading/Visual Logger.md",
    "Others/Summareading/Outliner Spaced Repetitionの注意点.md",
    "Others/Summareading/InputAction-OneFingerAction.md",
    "Teino/image/Pasted image 20241213002534.png",
    "themes/blowfish/theme.toml",
    "themes/blowfish/tailwind.config.js",
    "themes/blowfish/static/site.webmanifest",
    "themes/blowfish/static/favicon.ico",
    "themes/blowfish/static/favicon-16x16.png",
    "themes/blowfish/static/favicon-32x32.png",
    "themes/blowfish/static/apple-touch-icon.png",
    "themes/blowfish/static/android-chrome-512x512.png",
    "themes/blowfish/static/android-chrome-192x192.png",
    "themes/blowfish/static",
    "themes/blowfish/release-versions/hugo-latest.txt",
    "themes/blowfish/release-versions",
    "themes/blowfish/processUsers.js",
    "themes/blowfish/package.json",
    "themes/blowfish/logo.png",
    "themes/blowfish/images/tn.png",
    "themes/blowfish/images/screenshot.png",
    "public/novel/Timeline/Untitled.canvas"
  ]
}